MANIFEST.in
README.rst
setup.py
aliyun_python_sdk_uis.egg-info/PKG-INFO
aliyun_python_sdk_uis.egg-info/SOURCES.txt
aliyun_python_sdk_uis.egg-info/dependency_links.txt
aliyun_python_sdk_uis.egg-info/requires.txt
aliyun_python_sdk_uis.egg-info/top_level.txt
aliyunsdkuis/__init__.py
aliyunsdkuis/endpoint.py
aliyunsdkuis/request/__init__.py
aliyunsdkuis/request/v20180821/AddHighPriorityIpRequest.py
aliyunsdkuis/request/v20180821/AddUisNodeIpRequest.py
aliyunsdkuis/request/v20180821/CreateDnatEntryRequest.py
aliyunsdkuis/request/v20180821/CreateSubConnectionRequest.py
aliyunsdkuis/request/v20180821/CreateUisConnectionRequest.py
aliyunsdkuis/request/v20180821/CreateUisNetworkInterfaceRequest.py
aliyunsdkuis/request/v20180821/CreateUisNodeRequest.py
aliyunsdkuis/request/v20180821/CreateUisRequest.py
aliyunsdkuis/request/v20180821/DeleteDnatEntryRequest.py
aliyunsdkuis/request/v20180821/DeleteHighPriorityIpRequest.py
aliyunsdkuis/request/v20180821/DeleteSubConnectionRequest.py
aliyunsdkuis/request/v20180821/DeleteUisConnectionRequest.py
aliyunsdkuis/request/v20180821/DeleteUisNetworkInterfaceRequest.py
aliyunsdkuis/request/v20180821/DeleteUisNodeIpRequest.py
aliyunsdkuis/request/v20180821/DeleteUisNodeRequest.py
aliyunsdkuis/request/v20180821/DeleteUisRequest.py
aliyunsdkuis/request/v20180821/DescribeAreasRequest.py
aliyunsdkuis/request/v20180821/DescribeDnatEntriesRequest.py
aliyunsdkuis/request/v20180821/DescribeHighPriorityIpRequest.py
aliyunsdkuis/request/v20180821/DescribeHighPriorityIpsRequest.py
aliyunsdkuis/request/v20180821/DescribeRegionsRequest.py
aliyunsdkuis/request/v20180821/DescribeSubConnectionRequest.py
aliyunsdkuis/request/v20180821/DescribeSubConnectionsRequest.py
aliyunsdkuis/request/v20180821/DescribeUisConnectionsRequest.py
aliyunsdkuis/request/v20180821/DescribeUisNetworkInterfacesRequest.py
aliyunsdkuis/request/v20180821/DescribeUisNodesRequest.py
aliyunsdkuis/request/v20180821/DescribeUiseNodeStatusRequest.py
aliyunsdkuis/request/v20180821/DescribeUisesRequest.py
aliyunsdkuis/request/v20180821/DescribeWhiteListRequest.py
aliyunsdkuis/request/v20180821/GetDroppedIpListRequest.py
aliyunsdkuis/request/v20180821/ModifyDnatEntryRequest.py
